{
  "created": "2026-05-21T21:22:44Z",
  "mode": "source-prep-docling-discovery",
  "dry_run": false,
  "agent": "source-prep-docling-discovery",
  "limit": 0,
  "scan_limit": 300,
  "max_pages_per_source": 0,
  "ocr_limit": 12,
  "parallelism": 4,
  "ocr_parallelism": 2,
  "checkpoint_every": 1,
  "use_ocr": true,
  "document_timeout": 45.0,
  "hard_timeout": 45.0,
  "queue_scope": "source-prep-batches",
  "queue_task_count": 1453,
  "filters": {
    "source": "",
    "source_sha256": ""
  },
  "inspected": 12,
  "accepted": 0,
  "unusable": 1,
  "fast_unusable": 0,
  "errors": 11,
  "extracted_images": 0,
  "skipped": {
    "cached_error": 66,
    "ocr_limit_reached": 1042
  },
  "tasks": [
    {
      "task_id": "source-prep:ca9010aa1a-s495-2-2-p0351-0375-s495-2-2-pages-351-375:p0365",
      "source": "raw/sources/S495-2-2.pdf",
      "page": 365,
      "docling_ocr": true,
      "status": "error",
      "error": "[Errno 2] No such file or directory: '/home/runner/work/Genealogy-/Genealogy-/.easyocr/model/temp.zip'; Tesseract fallback failed: Tesseract process timeout"
    },
    {
      "task_id": "source-prep:ca9010aa1a-s495-2-2-p0351-0375-s495-2-2-pages-351-375:p0371",
      "source": "raw/sources/S495-2-2.pdf",
      "page": 371,
      "docling_ocr": true,
      "status": "error",
      "error": "Docling hard timeout after 45 seconds.; Tesseract fallback failed: Tesseract process timeout"
    },
    {
      "task_id": "source-prep:ca9010aa1a-s495-2-2-p0276-0300-s495-2-2-pages-276-300:p0284",
      "source": "raw/sources/S495-2-2.pdf",
      "page": 284,
      "docling_ocr": true,
      "status": "error",
      "error": "Docling hard timeout after 45 seconds.; Tesseract fallback failed: Tesseract process timeout"
    },
    {
      "task_id": "source-prep:ca9010aa1a-s495-2-2-p0326-0350-s495-2-2-pages-326-350:p0329",
      "source": "raw/sources/S495-2-2.pdf",
      "page": 329,
      "status": "rough_unusable",
      "discovery_path": "raw/discovery/docling/ca9010aa1a-s495-2-2-p0326-0350-s495-2-2-pages-326-350/page-0329.md",
      "readability_flags": [
        "docling_layout_noise"
      ],
      "profile_version": 6,
      "text_chars": 1843,
      "extracted_image_count": 0,
      "docling_ocr": true,
      "tesseract_after_docling_error": true,
      "docling_error": "Docling hard timeout after 45 seconds.",
      "text_layer_alpha_chars": 16039,
      "likely_full_page_scan": true,
      "text_layer_flags": [
        "encoding_mojibake",
        "fragmented_short_lines",
        "docling_layout_noise"
      ]
    },
    {
      "task_id": "source-prep:ca9010aa1a-s495-2-2-p0276-0300-s495-2-2-pages-276-300:p0295",
      "source": "raw/sources/S495-2-2.pdf",
      "page": 295,
      "docling_ocr": true,
      "status": "error",
      "error": "Docling hard timeout after 45 seconds.; Tesseract fallback failed: Tesseract process timeout"
    },
    {
      "task_id": "source-prep:ca9010aa1a-s495-2-2-p0451-0475-s495-2-2-pages-451-475:p0455",
      "source": "raw/sources/S495-2-2.pdf",
      "page": 455,
      "docling_ocr": true,
      "status": "error",
      "error": "Docling hard timeout after 45 seconds.; Tesseract fallback failed: Tesseract process timeout"
    },
    {
      "task_id": "source-prep:ca9010aa1a-s495-2-2-p0351-0375-s495-2-2-pages-351-375:p0359",
      "source": "raw/sources/S495-2-2.pdf",
      "page": 359,
      "docling_ocr": true,
      "status": "error",
      "error": "Docling hard timeout after 45 seconds.; Tesseract fallback failed: Tesseract process timeout"
    },
    {
      "task_id": "source-prep:ca9010aa1a-s495-2-2-p0351-0375-s495-2-2-pages-351-375:p0370",
      "source": "raw/sources/S495-2-2.pdf",
      "page": 370,
      "docling_ocr": true,
      "status": "error",
      "error": "Docling hard timeout after 45 seconds.; Tesseract fallback failed: Tesseract process timeout"
    },
    {
      "task_id": "source-prep:ca9010aa1a-s495-2-2-p0226-0250-s495-2-2-pages-226-250:p0242",
      "source": "raw/sources/S495-2-2.pdf",
      "page": 242,
      "docling_ocr": true,
      "status": "error",
      "error": "Docling hard timeout after 45 seconds.; Tesseract fallback failed: Tesseract process timeout"
    },
    {
      "task_id": "source-prep:ca9010aa1a-s495-2-2-p0376-0400-s495-2-2-pages-376-400:p0397",
      "source": "raw/sources/S495-2-2.pdf",
      "page": 397,
      "docling_ocr": true,
      "status": "error",
      "error": "Docling hard timeout after 45 seconds.; Tesseract fallback failed: Tesseract process timeout"
    },
    {
      "task_id": "source-prep:ca9010aa1a-s495-2-2-p0351-0375-s495-2-2-pages-351-375:p0369",
      "source": "raw/sources/S495-2-2.pdf",
      "page": 369,
      "docling_ocr": true,
      "status": "error",
      "error": "Docling hard timeout after 45 seconds.; Tesseract fallback failed: Tesseract process timeout"
    },
    {
      "task_id": "source-prep:ca9010aa1a-s495-2-2-p0426-0450-s495-2-2-pages-426-450:p0442",
      "source": "raw/sources/S495-2-2.pdf",
      "page": 442,
      "docling_ocr": true,
      "status": "error",
      "error": "Docling hard timeout after 45 seconds.; Tesseract fallback failed: Tesseract process timeout"
    }
  ],
  "blockers": [],
  "discovery_state_path": "research/_agent-queues/source-prep-discovery.json",
  "checkpointed": "2026-05-21T21:29:09Z",
  "state_path": "research/_automation/source-prep-docling-state.json",
  "finished": "2026-05-21T21:29:09Z"
}